Workbook

Sheet Read Me
B2: LOREMEX · NRR INTELLIGENCE
B3: Online Assessment — Dropdown Rubric Edition
B5: What this is
B6: Self-diagnostic for revenue, CS, and finance leaders. Four blocks: NRR Reporting (how the number is measured) plus three action capabilities (Retention, Expansion, Pricing Optimization). Each block has 7 rows × 4 dimensions; each dimension cell is a dropdown — pick the level (1–5) whose description matches your reality and the cell auto-populates with that description.
B8: How it works
B9: For each lever, read the lever question. Then for each of the 4 dimensions (People, Process, Technology, Data), click the dropdown — you'll see 5 descriptors of what each maturity level looks like. Pick the one that matches your current state. The cell fills with that descriptor, and the level number drives all the rollups.
B11: 1. | C11: NRR Calculator | D11: Tab '1. NRR' — enter the four MRR components. Outputs: NRR, GRR, net movement.
B12: 2. | C12: Assessment | D12: Tab '2. Assessment' — 112 dropdown cells (28 per capability block). Pick the level descriptor for each. Start with NRR Reporting (foundational) before the 3 action blocks.
B13: 3. | C13: Scorecard | D13: Tab '3. Scorecard' — cross-capability dimension view, per-capability heatmaps, lever and dimension rollups.
B14: 4. | C14: Rubric | D14: Tab '4. Rubric' — full L1-L5 ladder for each (lever × dimension), intelligence ladder, 7-lever framework with PRD weights.
B16: The Intelligence Ladder
B17: Every dropdown uses this 5-level ladder. Names match the Loremex PRD scale.
B19: Level | C19: Name | D19: Posture | E19: What it looks like
B20: 1 | C20: Ad Hoc | D20: Blind — No reliable view; instinct-driven decisions; people-only, no tooling or data substrate.
B21: 2 | C21: Assigned | D21: Reactive — Data is captured somewhere but used after the fact; manual stitching; a few people do the work.
B22: 3 | C22: Accountable | D22: Diagnostic — Data is joined and tooled; team can answer 'why' with effort; standardized process; clear ownership.
B23: 4 | C23: Optimised | D23: Predictive — Systems flag what's coming; near-real-time signals route work; closed-loop measurement and governance.
B24: 5 | C24: Predictive | D24: Intelligent — System senses, predicts, recommends, acts, and learns; continuously refined; effort is leveraged.
B26: Notes
B27: • Yellow cells = your inputs (the dropdowns). Blank = skip; excluded from rollups.
B28: • Lever Avg = average of the 4 dimension scores for that lever.
B29: • Capability Overall = lever-weighted average using PRD weights (L1 18%, L2 12%, L3 10%, L4 12%, L5 15%, L6 18%, L7 15%).
B30: • Cross-capability Dim Avg shows which dimensions are weak system-wide — your horizontal investment thesis.
B31: • Each capability has its own dropdown rubric — NRR Reporting uses M1-M7 measurement categories with FOUNDATION / RIGOR / DISTRIBUTE themes; the three action capabilities use the L1-L7 PRD levers with PROVE / SELL / REINFORCE themes.

Sheet 1. NRR
B2: LOREMEX · NRR INTELLIGENCE
B3: Preliminary NRR
B4: Enter the four components for your most recent measured period. NRR and GRR compute below.
B6: NRR = ( Starting MRR + Expansion − Contraction − Churn ) ÷ Starting MRR
B8: INPUTS
B9: Component | C9: Definition | D9: Excludes | E9: Value ($)
B10: Starting MRR | C10: Cohort base — accounts active in both baseline months. | D10: New-logo revenue; accounts in only one baseline month.
B11: Expansion MRR | C11: Positive recurring delta within retained accounts. | D11: New logos; reactivation of churned accounts.
B12: Contraction MRR | C12: Negative recurring delta within retained accounts. | D12: Full-logo loss (that is churn).
B13: Churn MRR | C13: Full-logo loss: account recurring revenue → $0 vs prior period. | D13: Partial downgrades (those are contraction).
B16: OUTPUTS
B17: Metric | C17: Formula | D17: Result | E17: Interpretation
B18: NRR | C18: (Start + Exp − Contr − Churn) ÷ Start | D18: =IF(OR(E10="",E10=0),"",(E10+IFERROR(E11,0)-IFERROR(E12,0)-IFERROR(E13,0))/E10) | E18: =IF(D18="","Enter the four components",IF(D18>=1.2,"World-class — best-in-class PE territory",IF(D18>=1.1,"Strong — PE investment threshold",IF(D18>=1,"Net positive — but exposed",IF(D18>=0.9,"Eroding base — material risk","Significant decline — urgent attention"))))) -> Enter the four components
B19: GRR | C19: (Start − Contr − Churn) ÷ Start | D19: =IF(OR(E10="",E10=0),"",(E10-IFERROR(E12,0)-IFERROR(E13,0))/E10) | E19: Retention-only — strip out expansion to see the base on its own
B20: Net Movement | C20: Exp − Contr − Churn | D20: =IFERROR(E11,0)-IFERROR(E12,0)-IFERROR(E13,0) -> 0 | E20: =IF(D20=0,"-",IF(D20>0,"Net expansion within cohort","Net contraction within cohort")) -> -

Sheet 2. Assessment
B2: LOREMEX · NRR INTELLIGENCE
B3: Intelligence Assessment
B4: 112 dropdowns — 4 capability blocks of (7 rows × 4 dimensions). Start with NRR Reporting (how the number is measured) before the 3 action capabilities. Click any dimension cell to open the dropdown; pick the level (1–5) whose description matches your reality and the cell fills with that descriptor.
B5: Scale: 1 — Ad Hoc (Blind) · 2 — Assigned (Reactive) · 3 — Accountable (Diagnostic) · 4 — Optimised (Predictive) · 5 — Predictive (Intelligent)
B7: NRR REPORTING
B8: How the company defines, calculates, and reports the NRR number itself.
B9: Category | C9: Name | D9: Theme | E9: Question | F9: Pick the answer that best matches your reality | J9: Level
B10: M1 | C10: Definition & Scope | D10: FOUNDATION | E10: Can every NRR conversation anchor in a single, documented, agreed-upon definition — including netting rules, cohort lock, and component scope? | J10: =IF(K10="","",K10) | K10: =IF(F10="","",VALUE(LEFT(F10,1)))
B11: M2 | C11: Component Capture | D11: FOUNDATION | E11: Can the company capture Starting MRR, Expansion, Contraction, and Churn cleanly per period without manual stitching or reconciliation pain? | J11: =IF(K11="","",K11) | K11: =IF(F11="","",VALUE(LEFT(F11,1)))
B12: M3 | C12: Calculation Method | D12: RIGOR | E12: Is the NRR calculation automated, version-controlled, auditable, and reproducible across periods — or does the number change depending on who runs it? | J12: =IF(K12="","",K12) | K12: =IF(F12="","",VALUE(LEFT(F12,1)))
B13: M4 | C13: Granularity | D13: RIGOR | E13: Can NRR be sliced by product, segment, cohort, tenure, and geo on demand — with consistent definitions across every cut? | J13: =IF(K13="","",K13) | K13: =IF(F13="","",VALUE(LEFT(F13,1)))
B14: M5 | C14: Cadence | D14: DISTRIBUTE | E14: Is NRR refreshed at a cadence that makes it actionable — or is the latest number weeks behind reality? | J14: =IF(K14="","",K14) | K14: =IF(F14="","",VALUE(LEFT(F14,1)))
B15: M6 | C15: Trust & Distribution | D15: DISTRIBUTE | E15: Is the NRR number trusted at exec and board levels — informing strategic decisions and valuation — or disputed at every readout? | J15: =IF(K15="","",K15) | K15: =IF(F15="","",VALUE(LEFT(F15,1)))
B16: M7 | C16: Forward-Looking | D16: DISTRIBUTE | E16: Does NRR reporting include leading indicators and forecast that flag trajectory before the number moves — or is it strictly backward-looking? | J16: =IF(K16="","",K16) | K16: =IF(F16="","",VALUE(LEFT(F16,1)))
B17: Capability Overall (weighted) | J17: =IF((IF(ISNUMBER(J10),0.18,0)+IF(ISNUMBER(J11),0.15,0)+IF(ISNUMBER(J12),0.15,0)+IF(ISNUMBER(J13),0.12,0)+IF(ISNUMBER(J14),0.12,0)+IF(ISNUMBER(J15),0.15,0)+IF(ISNUMBER(J16),0.13,0))=0,"",(IF(ISNUMBER(J10),J10*0.18,0)+IF(ISNUMBER(J11),J11*0.15,0)+IF(ISNUMBER(J12),J12*0.15,0)+IF(ISNUMBER(J13),J13*0.12,0)+IF(ISNUMBER(J14),J14*0.12,0)+IF(ISNUMBER(J15),J15*0.15,0)+IF(ISNUMBER(J16),J16*0.13,0))/(IF(ISNUMBER(J10),0.18,0)+IF(ISNUMBER(J11),0.15,0)+IF(ISNUMBER(J12),0.15,0)+IF(ISNUMBER(J13),0.12,0)+IF(ISNUMBER(J14),0.12,0)+IF(ISNUMBER(J15),0.15,0)+IF(ISNUMBER(J16),0.13,0)))
B19: REVENUE RETENTION
B20: Defending the installed base — preventing churn and contraction.
B21: Lever | C21: Name | D21: Theme | E21: Question | F21: People | G21: Process | H21: Technology | I21: Data | J21: Lever Avg
B22: L1 | C22: Impact Engine | D22: PROVE | E22: Can the company sense realized value per account, predict where it's slipping, and act on the evidence before renewal? | J22: =IF((IF(ISNUMBER(K22),1,0)+IF(ISNUMBER(L22),1,0)+IF(ISNUMBER(M22),1,0)+IF(ISNUMBER(N22),1,0))=0,"",(IF(ISNUMBER(K22),K22,0)+IF(ISNUMBER(L22),L22,0)+IF(ISNUMBER(M22),M22,0)+IF(ISNUMBER(N22),N22,0))/(IF(ISNUMBER(K22),1,0)+IF(ISNUMBER(L22),1,0)+IF(ISNUMBER(M22),1,0)+IF(ISNUMBER(N22),1,0))) | K22: =IF(F22="","",VALUE(LEFT(F22,1))) | L22: =IF(G22="","",VALUE(LEFT(G22,1))) | M22: =IF(H22="","",VALUE(LEFT(H22,1))) | N22: =IF(I22="","",VALUE(LEFT(I22,1)))
B23: L2 | C23: Whitespace | D23: PROVE | E23: Can the company sense renewal risk and adoption gaps, predict where they'll surface, and route the right intervention in time? | J23: =IF((IF(ISNUMBER(K23),1,0)+IF(ISNUMBER(L23),1,0)+IF(ISNUMBER(M23),1,0)+IF(ISNUMBER(N23),1,0))=0,"",(IF(ISNUMBER(K23),K23,0)+IF(ISNUMBER(L23),L23,0)+IF(ISNUMBER(M23),M23,0)+IF(ISNUMBER(N23),N23,0))/(IF(ISNUMBER(K23),1,0)+IF(ISNUMBER(L23),1,0)+IF(ISNUMBER(M23),1,0)+IF(ISNUMBER(N23),1,0))) | K23: =IF(F23="","",VALUE(LEFT(F23,1))) | L23: =IF(G23="","",VALUE(LEFT(G23,1))) | M23: =IF(H23="","",VALUE(LEFT(H23,1))) | N23: =IF(I23="","",VALUE(LEFT(I23,1)))
B24: L3 | C24: Account Plan | D24: SELL | E24: Can the company plan retention moves anchored in live signals, and refine plans as account reality evolves? | J24: =IF((IF(ISNUMBER(K24),1,0)+IF(ISNUMBER(L24),1,0)+IF(ISNUMBER(M24),1,0)+IF(ISNUMBER(N24),1,0))=0,"",(IF(ISNUMBER(K24),K24,0)+IF(ISNUMBER(L24),L24,0)+IF(ISNUMBER(M24),M24,0)+IF(ISNUMBER(N24),N24,0))/(IF(ISNUMBER(K24),1,0)+IF(ISNUMBER(L24),1,0)+IF(ISNUMBER(M24),1,0)+IF(ISNUMBER(N24),1,0))) | K24: =IF(F24="","",VALUE(LEFT(F24,1))) | L24: =IF(G24="","",VALUE(LEFT(G24,1))) | M24: =IF(H24="","",VALUE(LEFT(H24,1))) | N24: =IF(I24="","",VALUE(LEFT(I24,1)))
B25: L4 | C25: Plays | D25: SELL | E25: Can the company detect retention triggers (sponsor change, usage drop, support spike), route the right play, and learn which plays land? | J25: =IF((IF(ISNUMBER(K25),1,0)+IF(ISNUMBER(L25),1,0)+IF(ISNUMBER(M25),1,0)+IF(ISNUMBER(N25),1,0))=0,"",(IF(ISNUMBER(K25),K25,0)+IF(ISNUMBER(L25),L25,0)+IF(ISNUMBER(M25),M25,0)+IF(ISNUMBER(N25),N25,0))/(IF(ISNUMBER(K25),1,0)+IF(ISNUMBER(L25),1,0)+IF(ISNUMBER(M25),1,0)+IF(ISNUMBER(N25),1,0))) | K25: =IF(F25="","",VALUE(LEFT(F25,1))) | L25: =IF(G25="","",VALUE(LEFT(G25,1))) | M25: =IF(H25="","",VALUE(LEFT(H25,1))) | N25: =IF(I25="","",VALUE(LEFT(I25,1)))
B26: L5 | C26: Execution | D26: SELL | E26: Can the team execute the renewal motion with intelligence flowing through every stage gate — value, fit, risk, commit, close? | J26: =IF((IF(ISNUMBER(K26),1,0)+IF(ISNUMBER(L26),1,0)+IF(ISNUMBER(M26),1,0)+IF(ISNUMBER(N26),1,0))=0,"",(IF(ISNUMBER(K26),K26,0)+IF(ISNUMBER(L26),L26,0)+IF(ISNUMBER(M26),M26,0)+IF(ISNUMBER(N26),N26,0))/(IF(ISNUMBER(K26),1,0)+IF(ISNUMBER(L26),1,0)+IF(ISNUMBER(M26),1,0)+IF(ISNUMBER(N26),1,0))) | K26: =IF(F26="","",VALUE(LEFT(F26,1))) | L26: =IF(G26="","",VALUE(LEFT(G26,1))) | M26: =IF(H26="","",VALUE(LEFT(H26,1))) | N26: =IF(I26="","",VALUE(LEFT(I26,1)))
B27: L6 | C27: Incentives | D27: REINFORCE | E27: Is comp tuned by clean attribution and outcome data so reps are paid for the retention behavior that actually moves GRR? | J27: =IF((IF(ISNUMBER(K27),1,0)+IF(ISNUMBER(L27),1,0)+IF(ISNUMBER(M27),1,0)+IF(ISNUMBER(N27),1,0))=0,"",(IF(ISNUMBER(K27),K27,0)+IF(ISNUMBER(L27),L27,0)+IF(ISNUMBER(M27),M27,0)+IF(ISNUMBER(N27),N27,0))/(IF(ISNUMBER(K27),1,0)+IF(ISNUMBER(L27),1,0)+IF(ISNUMBER(M27),1,0)+IF(ISNUMBER(N27),1,0))) | K27: =IF(F27="","",VALUE(LEFT(F27,1))) | L27: =IF(G27="","",VALUE(LEFT(G27,1))) | M27: =IF(H27="","",VALUE(LEFT(H27,1))) | N27: =IF(I27="","",VALUE(LEFT(I27,1)))
B28: L7 | C28: Governance | D28: REINFORCE | E28: Can leadership govern retention with predictive intelligence — flagging trend reversals before they show up in reported NRR? | J28: =IF((IF(ISNUMBER(K28),1,0)+IF(ISNUMBER(L28),1,0)+IF(ISNUMBER(M28),1,0)+IF(ISNUMBER(N28),1,0))=0,"",(IF(ISNUMBER(K28),K28,0)+IF(ISNUMBER(L28),L28,0)+IF(ISNUMBER(M28),M28,0)+IF(ISNUMBER(N28),N28,0))/(IF(ISNUMBER(K28),1,0)+IF(ISNUMBER(L28),1,0)+IF(ISNUMBER(M28),1,0)+IF(ISNUMBER(N28),1,0))) | K28: =IF(F28="","",VALUE(LEFT(F28,1))) | L28: =IF(G28="","",VALUE(LEFT(G28,1))) | M28: =IF(H28="","",VALUE(LEFT(H28,1))) | N28: =IF(I28="","",VALUE(LEFT(I28,1)))
B29: Dim Avg (weighted) | F29: =IF((IF(ISNUMBER(K22),0.18,0)+IF(ISNUMBER(K23),0.12,0)+IF(ISNUMBER(K24),0.1,0)+IF(ISNUMBER(K25),0.12,0)+IF(ISNUMBER(K26),0.15,0)+IF(ISNUMBER(K27),0.18,0)+IF(ISNUMBER(K28),0.15,0))=0,"",(IF(ISNUMBER(K22),K22*0.18,0)+IF(ISNUMBER(K23),K23*0.12,0)+IF(ISNUMBER(K24),K24*0.1,0)+IF(ISNUMBER(K25),K25*0.12,0)+IF(ISNUMBER(K26),K26*0.15,0)+IF(ISNUMBER(K27),K27*0.18,0)+IF(ISNUMBER(K28),K28*0.15,0))/(IF(ISNUMBER(K22),0.18,0)+IF(ISNUMBER(K23),0.12,0)+IF(ISNUMBER(K24),0.1,0)+IF(ISNUMBER(K25),0.12,0)+IF(ISNUMBER(K26),0.15,0)+IF(ISNUMBER(K27),0.18,0)+IF(ISNUMBER(K28),0.15,0))) | G29: =IF((IF(ISNUMBER(L22),0.18,0)+IF(ISNUMBER(L23),0.12,0)+IF(ISNUMBER(L24),0.1,0)+IF(ISNUMBER(L25),0.12,0)+IF(ISNUMBER(L26),0.15,0)+IF(ISNUMBER(L27),0.18,0)+IF(ISNUMBER(L28),0.15,0))=0,"",(IF(ISNUMBER(L22),L22*0.18,0)+IF(ISNUMBER(L23),L23*0.12,0)+IF(ISNUMBER(L24),L24*0.1,0)+IF(ISNUMBER(L25),L25*0.12,0)+IF(ISNUMBER(L26),L26*0.15,0)+IF(ISNUMBER(L27),L27*0.18,0)+IF(ISNUMBER(L28),L28*0.15,0))/(IF(ISNUMBER(L22),0.18,0)+IF(ISNUMBER(L23),0.12,0)+IF(ISNUMBER(L24),0.1,0)+IF(ISNUMBER(L25),0.12,0)+IF(ISNUMBER(L26),0.15,0)+IF(ISNUMBER(L27),0.18,0)+IF(ISNUMBER(L28),0.15,0))) | H29: =IF((IF(ISNUMBER(M22),0.18,0)+IF(ISNUMBER(M23),0.12,0)+IF(ISNUMBER(M24),0.1,0)+IF(ISNUMBER(M25),0.12,0)+IF(ISNUMBER(M26),0.15,0)+IF(ISNUMBER(M27),0.18,0)+IF(ISNUMBER(M28),0.15,0))=0,"",(IF(ISNUMBER(M22),M22*0.18,0)+IF(ISNUMBER(M23),M23*0.12,0)+IF(ISNUMBER(M24),M24*0.1,0)+IF(ISNUMBER(M25),M25*0.12,0)+IF(ISNUMBER(M26),M26*0.15,0)+IF(ISNUMBER(M27),M27*0.18,0)+IF(ISNUMBER(M28),M28*0.15,0))/(IF(ISNUMBER(M22),0.18,0)+IF(ISNUMBER(M23),0.12,0)+IF(ISNUMBER(M24),0.1,0)+IF(ISNUMBER(M25),0.12,0)+IF(ISNUMBER(M26),0.15,0)+IF(ISNUMBER(M27),0.18,0)+IF(ISNUMBER(M28),0.15,0))) | I29: =IF((IF(ISNUMBER(N22),0.18,0)+IF(ISNUMBER(N23),0.12,0)+IF(ISNUMBER(N24),0.1,0)+IF(ISNUMBER(N25),0.12,0)+IF(ISNUMBER(N26),0.15,0)+IF(ISNUMBER(N27),0.18,0)+IF(ISNUMBER(N28),0.15,0))=0,"",(IF(ISNUMBER(N22),N22*0.18,0)+IF(ISNUMBER(N23),N23*0.12,0)+IF(ISNUMBER(N24),N24*0.1,0)+IF(ISNUMBER(N25),N25*0.12,0)+IF(ISNUMBER(N26),N26*0.15,0)+IF(ISNUMBER(N27),N27*0.18,0)+IF(ISNUMBER(N28),N28*0.15,0))/(IF(ISNUMBER(N22),0.18,0)+IF(ISNUMBER(N23),0.12,0)+IF(ISNUMBER(N24),0.1,0)+IF(ISNUMBER(N25),0.12,0)+IF(ISNUMBER(N26),0.15,0)+IF(ISNUMBER(N27),0.18,0)+IF(ISNUMBER(N28),0.15,0))) | J29: =IF((IF(ISNUMBER(J22),0.18,0)+IF(ISNUMBER(J23),0.12,0)+IF(ISNUMBER(J24),0.1,0)+IF(ISNUMBER(J25),0.12,0)+IF(ISNUMBER(J26),0.15,0)+IF(ISNUMBER(J27),0.18,0)+IF(ISNUMBER(J28),0.15,0))=0,"",(IF(ISNUMBER(J22),J22*0.18,0)+IF(ISNUMBER(J23),J23*0.12,0)+IF(ISNUMBER(J24),J24*0.1,0)+IF(ISNUMBER(J25),J25*0.12,0)+IF(ISNUMBER(J26),J26*0.15,0)+IF(ISNUMBER(J27),J27*0.18,0)+IF(ISNUMBER(J28),J28*0.15,0))/(IF(ISNUMBER(J22),0.18,0)+IF(ISNUMBER(J23),0.12,0)+IF(ISNUMBER(J24),0.1,0)+IF(ISNUMBER(J25),0.12,0)+IF(ISNUMBER(J26),0.15,0)+IF(ISNUMBER(J27),0.18,0)+IF(ISNUMBER(J28),0.15,0)))
B31: REVENUE EXPANSION
B32: Growing revenue within retained accounts — seats, tiers, cross-sell.
B33: Lever | C33: Name | D33: Theme | E33: Question | F33: People | G33: Process | H33: Technology | I33: Data | J33: Lever Avg
B34: L1 | C34: Impact Engine | D34: PROVE | E34: Can the company sense realized value per unit, predict where headroom is real, and trigger expansion conversations at the right moment? | J34: =IF((IF(ISNUMBER(K34),1,0)+IF(ISNUMBER(L34),1,0)+IF(ISNUMBER(M34),1,0)+IF(ISNUMBER(N34),1,0))=0,"",(IF(ISNUMBER(K34),K34,0)+IF(ISNUMBER(L34),L34,0)+IF(ISNUMBER(M34),M34,0)+IF(ISNUMBER(N34),N34,0))/(IF(ISNUMBER(K34),1,0)+IF(ISNUMBER(L34),1,0)+IF(ISNUMBER(M34),1,0)+IF(ISNUMBER(N34),1,0))) | K34: =IF(F34="","",VALUE(LEFT(F34,1))) | L34: =IF(G34="","",VALUE(LEFT(G34,1))) | M34: =IF(H34="","",VALUE(LEFT(H34,1))) | N34: =IF(I34="","",VALUE(LEFT(I34,1)))
B35: L2 | C35: Whitespace | D35: PROVE | E35: Can the company sense seat / usage / whitespace headroom, predict conversion likelihood, and route the right play to the right owner? | J35: =IF((IF(ISNUMBER(K35),1,0)+IF(ISNUMBER(L35),1,0)+IF(ISNUMBER(M35),1,0)+IF(ISNUMBER(N35),1,0))=0,"",(IF(ISNUMBER(K35),K35,0)+IF(ISNUMBER(L35),L35,0)+IF(ISNUMBER(M35),M35,0)+IF(ISNUMBER(N35),N35,0))/(IF(ISNUMBER(K35),1,0)+IF(ISNUMBER(L35),1,0)+IF(ISNUMBER(M35),1,0)+IF(ISNUMBER(N35),1,0))) | K35: =IF(F35="","",VALUE(LEFT(F35,1))) | L35: =IF(G35="","",VALUE(LEFT(G35,1))) | M35: =IF(H35="","",VALUE(LEFT(H35,1))) | N35: =IF(I35="","",VALUE(LEFT(I35,1)))
B36: L3 | C36: Account Plan | D36: SELL | E36: Can account plans pull live usage signals and adapt as the account changes — or are they static documents? | J36: =IF((IF(ISNUMBER(K36),1,0)+IF(ISNUMBER(L36),1,0)+IF(ISNUMBER(M36),1,0)+IF(ISNUMBER(N36),1,0))=0,"",(IF(ISNUMBER(K36),K36,0)+IF(ISNUMBER(L36),L36,0)+IF(ISNUMBER(M36),M36,0)+IF(ISNUMBER(N36),N36,0))/(IF(ISNUMBER(K36),1,0)+IF(ISNUMBER(L36),1,0)+IF(ISNUMBER(M36),1,0)+IF(ISNUMBER(N36),1,0))) | K36: =IF(F36="","",VALUE(LEFT(F36,1))) | L36: =IF(G36="","",VALUE(LEFT(G36,1))) | M36: =IF(H36="","",VALUE(LEFT(H36,1))) | N36: =IF(I36="","",VALUE(LEFT(I36,1)))
B37: L4 | C37: Plays | D37: SELL | E37: Can the company detect expansion triggers (nearing commit, overage, role change), route the right play, and learn which signals convert? | J37: =IF((IF(ISNUMBER(K37),1,0)+IF(ISNUMBER(L37),1,0)+IF(ISNUMBER(M37),1,0)+IF(ISNUMBER(N37),1,0))=0,"",(IF(ISNUMBER(K37),K37,0)+IF(ISNUMBER(L37),L37,0)+IF(ISNUMBER(M37),M37,0)+IF(ISNUMBER(N37),N37,0))/(IF(ISNUMBER(K37),1,0)+IF(ISNUMBER(L37),1,0)+IF(ISNUMBER(M37),1,0)+IF(ISNUMBER(N37),1,0))) | K37: =IF(F37="","",VALUE(LEFT(F37,1))) | L37: =IF(G37="","",VALUE(LEFT(G37,1))) | M37: =IF(H37="","",VALUE(LEFT(H37,1))) | N37: =IF(I37="","",VALUE(LEFT(I37,1)))
B38: L5 | C38: Execution | D38: SELL | E38: Can the team execute the usage-up motion with intelligence at every stage — confirm value, diagnose, tailor, trade, close? | J38: =IF((IF(ISNUMBER(K38),1,0)+IF(ISNUMBER(L38),1,0)+IF(ISNUMBER(M38),1,0)+IF(ISNUMBER(N38),1,0))=0,"",(IF(ISNUMBER(K38),K38,0)+IF(ISNUMBER(L38),L38,0)+IF(ISNUMBER(M38),M38,0)+IF(ISNUMBER(N38),N38,0))/(IF(ISNUMBER(K38),1,0)+IF(ISNUMBER(L38),1,0)+IF(ISNUMBER(M38),1,0)+IF(ISNUMBER(N38),1,0))) | K38: =IF(F38="","",VALUE(LEFT(F38,1))) | L38: =IF(G38="","",VALUE(LEFT(G38,1))) | M38: =IF(H38="","",VALUE(LEFT(H38,1))) | N38: =IF(I38="","",VALUE(LEFT(I38,1)))
B39: L6 | C39: Incentives | D39: REINFORCE | E39: Is comp tuned by clean attribution and outcome data so reps are paid for the usage growth and tier-up that actually moves NRR? | J39: =IF((IF(ISNUMBER(K39),1,0)+IF(ISNUMBER(L39),1,0)+IF(ISNUMBER(M39),1,0)+IF(ISNUMBER(N39),1,0))=0,"",(IF(ISNUMBER(K39),K39,0)+IF(ISNUMBER(L39),L39,0)+IF(ISNUMBER(M39),M39,0)+IF(ISNUMBER(N39),N39,0))/(IF(ISNUMBER(K39),1,0)+IF(ISNUMBER(L39),1,0)+IF(ISNUMBER(M39),1,0)+IF(ISNUMBER(N39),1,0))) | K39: =IF(F39="","",VALUE(LEFT(F39,1))) | L39: =IF(G39="","",VALUE(LEFT(G39,1))) | M39: =IF(H39="","",VALUE(LEFT(H39,1))) | N39: =IF(I39="","",VALUE(LEFT(I39,1)))
B40: L7 | C40: Governance | D40: REINFORCE | E40: Can leadership govern expansion with predictive intelligence — sensing trajectory before it lands in the reported number? | J40: =IF((IF(ISNUMBER(K40),1,0)+IF(ISNUMBER(L40),1,0)+IF(ISNUMBER(M40),1,0)+IF(ISNUMBER(N40),1,0))=0,"",(IF(ISNUMBER(K40),K40,0)+IF(ISNUMBER(L40),L40,0)+IF(ISNUMBER(M40),M40,0)+IF(ISNUMBER(N40),N40,0))/(IF(ISNUMBER(K40),1,0)+IF(ISNUMBER(L40),1,0)+IF(ISNUMBER(M40),1,0)+IF(ISNUMBER(N40),1,0))) | K40: =IF(F40="","",VALUE(LEFT(F40,1))) | L40: =IF(G40="","",VALUE(LEFT(G40,1))) | M40: =IF(H40="","",VALUE(LEFT(H40,1))) | N40: =IF(I40="","",VALUE(LEFT(I40,1)))
B41: Dim Avg (weighted) | F41: =IF((IF(ISNUMBER(K34),0.18,0)+IF(ISNUMBER(K35),0.12,0)+IF(ISNUMBER(K36),0.1,0)+IF(ISNUMBER(K37),0.12,0)+IF(ISNUMBER(K38),0.15,0)+IF(ISNUMBER(K39),0.18,0)+IF(ISNUMBER(K40),0.15,0))=0,"",(IF(ISNUMBER(K34),K34*0.18,0)+IF(ISNUMBER(K35),K35*0.12,0)+IF(ISNUMBER(K36),K36*0.1,0)+IF(ISNUMBER(K37),K37*0.12,0)+IF(ISNUMBER(K38),K38*0.15,0)+IF(ISNUMBER(K39),K39*0.18,0)+IF(ISNUMBER(K40),K40*0.15,0))/(IF(ISNUMBER(K34),0.18,0)+IF(ISNUMBER(K35),0.12,0)+IF(ISNUMBER(K36),0.1,0)+IF(ISNUMBER(K37),0.12,0)+IF(ISNUMBER(K38),0.15,0)+IF(ISNUMBER(K39),0.18,0)+IF(ISNUMBER(K40),0.15,0))) | G41: =IF((IF(ISNUMBER(L34),0.18,0)+IF(ISNUMBER(L35),0.12,0)+IF(ISNUMBER(L36),0.1,0)+IF(ISNUMBER(L37),0.12,0)+IF(ISNUMBER(L38),0.15,0)+IF(ISNUMBER(L39),0.18,0)+IF(ISNUMBER(L40),0.15,0))=0,"",(IF(ISNUMBER(L34),L34*0.18,0)+IF(ISNUMBER(L35),L35*0.12,0)+IF(ISNUMBER(L36),L36*0.1,0)+IF(ISNUMBER(L37),L37*0.12,0)+IF(ISNUMBER(L38),L38*0.15,0)+IF(ISNUMBER(L39),L39*0.18,0)+IF(ISNUMBER(L40),L40*0.15,0))/(IF(ISNUMBER(L34),0.18,0)+IF(ISNUMBER(L35),0.12,0)+IF(ISNUMBER(L36),0.1,0)+IF(ISNUMBER(L37),0.12,0)+IF(ISNUMBER(L38),0.15,0)+IF(ISNUMBER(L39),0.18,0)+IF(ISNUMBER(L40),0.15,0))) | H41: =IF((IF(ISNUMBER(M34),0.18,0)+IF(ISNUMBER(M35),0.12,0)+IF(ISNUMBER(M36),0.1,0)+IF(ISNUMBER(M37),0.12,0)+IF(ISNUMBER(M38),0.15,0)+IF(ISNUMBER(M39),0.18,0)+IF(ISNUMBER(M40),0.15,0))=0,"",(IF(ISNUMBER(M34),M34*0.18,0)+IF(ISNUMBER(M35),M35*0.12,0)+IF(ISNUMBER(M36),M36*0.1,0)+IF(ISNUMBER(M37),M37*0.12,0)+IF(ISNUMBER(M38),M38*0.15,0)+IF(ISNUMBER(M39),M39*0.18,0)+IF(ISNUMBER(M40),M40*0.15,0))/(IF(ISNUMBER(M34),0.18,0)+IF(ISNUMBER(M35),0.12,0)+IF(ISNUMBER(M36),0.1,0)+IF(ISNUMBER(M37),0.12,0)+IF(ISNUMBER(M38),0.15,0)+IF(ISNUMBER(M39),0.18,0)+IF(ISNUMBER(M40),0.15,0))) | I41: =IF((IF(ISNUMBER(N34),0.18,0)+IF(ISNUMBER(N35),0.12,0)+IF(ISNUMBER(N36),0.1,0)+IF(ISNUMBER(N37),0.12,0)+IF(ISNUMBER(N38),0.15,0)+IF(ISNUMBER(N39),0.18,0)+IF(ISNUMBER(N40),0.15,0))=0,"",(IF(ISNUMBER(N34),N34*0.18,0)+IF(ISNUMBER(N35),N35*0.12,0)+IF(ISNUMBER(N36),N36*0.1,0)+IF(ISNUMBER(N37),N37*0.12,0)+IF(ISNUMBER(N38),N38*0.15,0)+IF(ISNUMBER(N39),N39*0.18,0)+IF(ISNUMBER(N40),N40*0.15,0))/(IF(ISNUMBER(N34),0.18,0)+IF(ISNUMBER(N35),0.12,0)+IF(ISNUMBER(N36),0.1,0)+IF(ISNUMBER(N37),0.12,0)+IF(ISNUMBER(N38),0.15,0)+IF(ISNUMBER(N39),0.18,0)+IF(ISNUMBER(N40),0.15,0))) | J41: =IF((IF(ISNUMBER(J34),0.18,0)+IF(ISNUMBER(J35),0.12,0)+IF(ISNUMBER(J36),0.1,0)+IF(ISNUMBER(J37),0.12,0)+IF(ISNUMBER(J38),0.15,0)+IF(ISNUMBER(J39),0.18,0)+IF(ISNUMBER(J40),0.15,0))=0,"",(IF(ISNUMBER(J34),J34*0.18,0)+IF(ISNUMBER(J35),J35*0.12,0)+IF(ISNUMBER(J36),J36*0.1,0)+IF(ISNUMBER(J37),J37*0.12,0)+IF(ISNUMBER(J38),J38*0.15,0)+IF(ISNUMBER(J39),J39*0.18,0)+IF(ISNUMBER(J40),J40*0.15,0))/(IF(ISNUMBER(J34),0.18,0)+IF(ISNUMBER(J35),0.12,0)+IF(ISNUMBER(J36),0.1,0)+IF(ISNUMBER(J37),0.12,0)+IF(ISNUMBER(J38),0.15,0)+IF(ISNUMBER(J39),0.18,0)+IF(ISNUMBER(J40),0.15,0)))
B43: PRICING OPTIMIZATION
B44: Setting, defending, and evolving price to capture earned value.
B45: Lever | C45: Name | D45: Theme | E45: Question | F45: People | G45: Process | H45: Technology | I45: Data | J45: Lever Avg
B46: L1 | C46: Impact Engine | D46: PROVE | E46: Can the company sense realized value, predict willingness-to-pay, and defend price with evidence at quote time — not cost-plus, not competitor? | J46: =IF((IF(ISNUMBER(K46),1,0)+IF(ISNUMBER(L46),1,0)+IF(ISNUMBER(M46),1,0)+IF(ISNUMBER(N46),1,0))=0,"",(IF(ISNUMBER(K46),K46,0)+IF(ISNUMBER(L46),L46,0)+IF(ISNUMBER(M46),M46,0)+IF(ISNUMBER(N46),N46,0))/(IF(ISNUMBER(K46),1,0)+IF(ISNUMBER(L46),1,0)+IF(ISNUMBER(M46),1,0)+IF(ISNUMBER(N46),1,0))) | K46: =IF(F46="","",VALUE(LEFT(F46,1))) | L46: =IF(G46="","",VALUE(LEFT(G46,1))) | M46: =IF(H46="","",VALUE(LEFT(H46,1))) | N46: =IF(I46="","",VALUE(LEFT(I46,1)))
B47: L2 | C47: Whitespace | D47: PROVE | E47: Can the company sense pricing leakage, predict where price-power exists, and route re-pricing or re-tiering before margin erodes? | J47: =IF((IF(ISNUMBER(K47),1,0)+IF(ISNUMBER(L47),1,0)+IF(ISNUMBER(M47),1,0)+IF(ISNUMBER(N47),1,0))=0,"",(IF(ISNUMBER(K47),K47,0)+IF(ISNUMBER(L47),L47,0)+IF(ISNUMBER(M47),M47,0)+IF(ISNUMBER(N47),N47,0))/(IF(ISNUMBER(K47),1,0)+IF(ISNUMBER(L47),1,0)+IF(ISNUMBER(M47),1,0)+IF(ISNUMBER(N47),1,0))) | K47: =IF(F47="","",VALUE(LEFT(F47,1))) | L47: =IF(G47="","",VALUE(LEFT(G47,1))) | M47: =IF(H47="","",VALUE(LEFT(H47,1))) | N47: =IF(I47="","",VALUE(LEFT(I47,1)))
B48: L3 | C48: Account Plan | D48: SELL | E48: Can pricing strategy adapt per segment from live win / loss and elasticity signals, with floors and tier targets that hold? | J48: =IF((IF(ISNUMBER(K48),1,0)+IF(ISNUMBER(L48),1,0)+IF(ISNUMBER(M48),1,0)+IF(ISNUMBER(N48),1,0))=0,"",(IF(ISNUMBER(K48),K48,0)+IF(ISNUMBER(L48),L48,0)+IF(ISNUMBER(M48),M48,0)+IF(ISNUMBER(N48),N48,0))/(IF(ISNUMBER(K48),1,0)+IF(ISNUMBER(L48),1,0)+IF(ISNUMBER(M48),1,0)+IF(ISNUMBER(N48),1,0))) | K48: =IF(F48="","",VALUE(LEFT(F48,1))) | L48: =IF(G48="","",VALUE(LEFT(G48,1))) | M48: =IF(H48="","",VALUE(LEFT(H48,1))) | N48: =IF(I48="","",VALUE(LEFT(I48,1)))
B49: L4 | C49: Plays | D49: SELL | E49: Can the company detect pricing triggers (discount > floor, tier-mismatch, repricing opportunity), route plays, and learn which decisions hold value? | J49: =IF((IF(ISNUMBER(K49),1,0)+IF(ISNUMBER(L49),1,0)+IF(ISNUMBER(M49),1,0)+IF(ISNUMBER(N49),1,0))=0,"",(IF(ISNUMBER(K49),K49,0)+IF(ISNUMBER(L49),L49,0)+IF(ISNUMBER(M49),M49,0)+IF(ISNUMBER(N49),N49,0))/(IF(ISNUMBER(K49),1,0)+IF(ISNUMBER(L49),1,0)+IF(ISNUMBER(M49),1,0)+IF(ISNUMBER(N49),1,0))) | K49: =IF(F49="","",VALUE(LEFT(F49,1))) | L49: =IF(G49="","",VALUE(LEFT(G49,1))) | M49: =IF(H49="","",VALUE(LEFT(H49,1))) | N49: =IF(I49="","",VALUE(LEFT(I49,1)))
B50: L5 | C50: Execution | D50: SELL | E50: Can the team execute pricing decisions with intelligence — anchor value, quote, defend, trade, close — instrumented and auditable? | J50: =IF((IF(ISNUMBER(K50),1,0)+IF(ISNUMBER(L50),1,0)+IF(ISNUMBER(M50),1,0)+IF(ISNUMBER(N50),1,0))=0,"",(IF(ISNUMBER(K50),K50,0)+IF(ISNUMBER(L50),L50,0)+IF(ISNUMBER(M50),M50,0)+IF(ISNUMBER(N50),N50,0))/(IF(ISNUMBER(K50),1,0)+IF(ISNUMBER(L50),1,0)+IF(ISNUMBER(M50),1,0)+IF(ISNUMBER(N50),1,0))) | K50: =IF(F50="","",VALUE(LEFT(F50,1))) | L50: =IF(G50="","",VALUE(LEFT(G50,1))) | M50: =IF(H50="","",VALUE(LEFT(H50,1))) | N50: =IF(I50="","",VALUE(LEFT(I50,1)))
B51: L6 | C51: Incentives | D51: REINFORCE | E51: Is comp tuned by clean attribution and outcome data so reps are paid for price discipline and tier-up, not just volume? | J51: =IF((IF(ISNUMBER(K51),1,0)+IF(ISNUMBER(L51),1,0)+IF(ISNUMBER(M51),1,0)+IF(ISNUMBER(N51),1,0))=0,"",(IF(ISNUMBER(K51),K51,0)+IF(ISNUMBER(L51),L51,0)+IF(ISNUMBER(M51),M51,0)+IF(ISNUMBER(N51),N51,0))/(IF(ISNUMBER(K51),1,0)+IF(ISNUMBER(L51),1,0)+IF(ISNUMBER(M51),1,0)+IF(ISNUMBER(N51),1,0))) | K51: =IF(F51="","",VALUE(LEFT(F51,1))) | L51: =IF(G51="","",VALUE(LEFT(G51,1))) | M51: =IF(H51="","",VALUE(LEFT(H51,1))) | N51: =IF(I51="","",VALUE(LEFT(I51,1)))
B52: L7 | C52: Governance | D52: REINFORCE | E52: Can leadership govern pricing with predictive intelligence — flagging price-power shifts before they hit ARPA and effective discount? | J52: =IF((IF(ISNUMBER(K52),1,0)+IF(ISNUMBER(L52),1,0)+IF(ISNUMBER(M52),1,0)+IF(ISNUMBER(N52),1,0))=0,"",(IF(ISNUMBER(K52),K52,0)+IF(ISNUMBER(L52),L52,0)+IF(ISNUMBER(M52),M52,0)+IF(ISNUMBER(N52),N52,0))/(IF(ISNUMBER(K52),1,0)+IF(ISNUMBER(L52),1,0)+IF(ISNUMBER(M52),1,0)+IF(ISNUMBER(N52),1,0))) | K52: =IF(F52="","",VALUE(LEFT(F52,1))) | L52: =IF(G52="","",VALUE(LEFT(G52,1))) | M52: =IF(H52="","",VALUE(LEFT(H52,1))) | N52: =IF(I52="","",VALUE(LEFT(I52,1)))
B53: Dim Avg (weighted) | F53: =IF((IF(ISNUMBER(K46),0.18,0)+IF(ISNUMBER(K47),0.12,0)+IF(ISNUMBER(K48),0.1,0)+IF(ISNUMBER(K49),0.12,0)+IF(ISNUMBER(K50),0.15,0)+IF(ISNUMBER(K51),0.18,0)+IF(ISNUMBER(K52),0.15,0))=0,"",(IF(ISNUMBER(K46),K46*0.18,0)+IF(ISNUMBER(K47),K47*0.12,0)+IF(ISNUMBER(K48),K48*0.1,0)+IF(ISNUMBER(K49),K49*0.12,0)+IF(ISNUMBER(K50),K50*0.15,0)+IF(ISNUMBER(K51),K51*0.18,0)+IF(ISNUMBER(K52),K52*0.15,0))/(IF(ISNUMBER(K46),0.18,0)+IF(ISNUMBER(K47),0.12,0)+IF(ISNUMBER(K48),0.1,0)+IF(ISNUMBER(K49),0.12,0)+IF(ISNUMBER(K50),0.15,0)+IF(ISNUMBER(K51),0.18,0)+IF(ISNUMBER(K52),0.15,0))) | G53: =IF((IF(ISNUMBER(L46),0.18,0)+IF(ISNUMBER(L47),0.12,0)+IF(ISNUMBER(L48),0.1,0)+IF(ISNUMBER(L49),0.12,0)+IF(ISNUMBER(L50),0.15,0)+IF(ISNUMBER(L51),0.18,0)+IF(ISNUMBER(L52),0.15,0))=0,"",(IF(ISNUMBER(L46),L46*0.18,0)+IF(ISNUMBER(L47),L47*0.12,0)+IF(ISNUMBER(L48),L48*0.1,0)+IF(ISNUMBER(L49),L49*0.12,0)+IF(ISNUMBER(L50),L50*0.15,0)+IF(ISNUMBER(L51),L51*0.18,0)+IF(ISNUMBER(L52),L52*0.15,0))/(IF(ISNUMBER(L46),0.18,0)+IF(ISNUMBER(L47),0.12,0)+IF(ISNUMBER(L48),0.1,0)+IF(ISNUMBER(L49),0.12,0)+IF(ISNUMBER(L50),0.15,0)+IF(ISNUMBER(L51),0.18,0)+IF(ISNUMBER(L52),0.15,0))) | H53: =IF((IF(ISNUMBER(M46),0.18,0)+IF(ISNUMBER(M47),0.12,0)+IF(ISNUMBER(M48),0.1,0)+IF(ISNUMBER(M49),0.12,0)+IF(ISNUMBER(M50),0.15,0)+IF(ISNUMBER(M51),0.18,0)+IF(ISNUMBER(M52),0.15,0))=0,"",(IF(ISNUMBER(M46),M46*0.18,0)+IF(ISNUMBER(M47),M47*0.12,0)+IF(ISNUMBER(M48),M48*0.1,0)+IF(ISNUMBER(M49),M49*0.12,0)+IF(ISNUMBER(M50),M50*0.15,0)+IF(ISNUMBER(M51),M51*0.18,0)+IF(ISNUMBER(M52),M52*0.15,0))/(IF(ISNUMBER(M46),0.18,0)+IF(ISNUMBER(M47),0.12,0)+IF(ISNUMBER(M48),0.1,0)+IF(ISNUMBER(M49),0.12,0)+IF(ISNUMBER(M50),0.15,0)+IF(ISNUMBER(M51),0.18,0)+IF(ISNUMBER(M52),0.15,0))) | I53: =IF((IF(ISNUMBER(N46),0.18,0)+IF(ISNUMBER(N47),0.12,0)+IF(ISNUMBER(N48),0.1,0)+IF(ISNUMBER(N49),0.12,0)+IF(ISNUMBER(N50),0.15,0)+IF(ISNUMBER(N51),0.18,0)+IF(ISNUMBER(N52),0.15,0))=0,"",(IF(ISNUMBER(N46),N46*0.18,0)+IF(ISNUMBER(N47),N47*0.12,0)+IF(ISNUMBER(N48),N48*0.1,0)+IF(ISNUMBER(N49),N49*0.12,0)+IF(ISNUMBER(N50),N50*0.15,0)+IF(ISNUMBER(N51),N51*0.18,0)+IF(ISNUMBER(N52),N52*0.15,0))/(IF(ISNUMBER(N46),0.18,0)+IF(ISNUMBER(N47),0.12,0)+IF(ISNUMBER(N48),0.1,0)+IF(ISNUMBER(N49),0.12,0)+IF(ISNUMBER(N50),0.15,0)+IF(ISNUMBER(N51),0.18,0)+IF(ISNUMBER(N52),0.15,0))) | J53: =IF((IF(ISNUMBER(J46),0.18,0)+IF(ISNUMBER(J47),0.12,0)+IF(ISNUMBER(J48),0.1,0)+IF(ISNUMBER(J49),0.12,0)+IF(ISNUMBER(J50),0.15,0)+IF(ISNUMBER(J51),0.18,0)+IF(ISNUMBER(J52),0.15,0))=0,"",(IF(ISNUMBER(J46),J46*0.18,0)+IF(ISNUMBER(J47),J47*0.12,0)+IF(ISNUMBER(J48),J48*0.1,0)+IF(ISNUMBER(J49),J49*0.12,0)+IF(ISNUMBER(J50),J50*0.15,0)+IF(ISNUMBER(J51),J51*0.18,0)+IF(ISNUMBER(J52),J52*0.15,0))/(IF(ISNUMBER(J46),0.18,0)+IF(ISNUMBER(J47),0.12,0)+IF(ISNUMBER(J48),0.1,0)+IF(ISNUMBER(J49),0.12,0)+IF(ISNUMBER(J50),0.15,0)+IF(ISNUMBER(J51),0.18,0)+IF(ISNUMBER(J52),0.15,0)))

Sheet 3. Scorecard
B2: LOREMEX · NRR INTELLIGENCE
B3: Your Scorecard
B4: Auto-calculated from the Assessment tab.
B6: HEADLINE METRICS
B7: NRR (preliminary) | D7: GRR | F7: Overall Intelligence | H7: Distance to Intelligent (L5)
B8: ='1. NRR'!D18 | D8: ='1. NRR'!D19 | F8: =IF((IF(ISNUMBER(C17),1,0)+IF(ISNUMBER(D17),1,0)+IF(ISNUMBER(E17),1,0))=0,"",(IF(ISNUMBER(C17),C17,0)+IF(ISNUMBER(D17),D17,0)+IF(ISNUMBER(E17),E17,0))/(IF(ISNUMBER(C17),1,0)+IF(ISNUMBER(D17),1,0)+IF(ISNUMBER(E17),1,0))) | H8: =IF(F8="","",5-F8)
B11: CROSS-CAPABILITY DIMENSION VIEW (action capabilities only)
B12: Dimension | C12: Revenue Retention | D12: Revenue Expansion | E12: Pricing Optimization | F12: Dim Avg | G12: Gap to L5
B13: People | C13: ='2. Assessment'!F29 | D13: ='2. Assessment'!F41 | E13: ='2. Assessment'!F53 | F13: =IF((IF(ISNUMBER(C13),1,0)+IF(ISNUMBER(D13),1,0)+IF(ISNUMBER(E13),1,0))=0,"",(IF(ISNUMBER(C13),C13,0)+IF(ISNUMBER(D13),D13,0)+IF(ISNUMBER(E13),E13,0))/(IF(ISNUMBER(C13),1,0)+IF(ISNUMBER(D13),1,0)+IF(ISNUMBER(E13),1,0))) | G13: =IF(F13="","",5-F13)
B14: Process | C14: ='2. Assessment'!G29 | D14: ='2. Assessment'!G41 | E14: ='2. Assessment'!G53 | F14: =IF((IF(ISNUMBER(C14),1,0)+IF(ISNUMBER(D14),1,0)+IF(ISNUMBER(E14),1,0))=0,"",(IF(ISNUMBER(C14),C14,0)+IF(ISNUMBER(D14),D14,0)+IF(ISNUMBER(E14),E14,0))/(IF(ISNUMBER(C14),1,0)+IF(ISNUMBER(D14),1,0)+IF(ISNUMBER(E14),1,0))) | G14: =IF(F14="","",5-F14)
B15: Technology | C15: ='2. Assessment'!H29 | D15: ='2. Assessment'!H41 | E15: ='2. Assessment'!H53 | F15: =IF((IF(ISNUMBER(C15),1,0)+IF(ISNUMBER(D15),1,0)+IF(ISNUMBER(E15),1,0))=0,"",(IF(ISNUMBER(C15),C15,0)+IF(ISNUMBER(D15),D15,0)+IF(ISNUMBER(E15),E15,0))/(IF(ISNUMBER(C15),1,0)+IF(ISNUMBER(D15),1,0)+IF(ISNUMBER(E15),1,0))) | G15: =IF(F15="","",5-F15)
B16: Data | C16: ='2. Assessment'!I29 | D16: ='2. Assessment'!I41 | E16: ='2. Assessment'!I53 | F16: =IF((IF(ISNUMBER(C16),1,0)+IF(ISNUMBER(D16),1,0)+IF(ISNUMBER(E16),1,0))=0,"",(IF(ISNUMBER(C16),C16,0)+IF(ISNUMBER(D16),D16,0)+IF(ISNUMBER(E16),E16,0))/(IF(ISNUMBER(C16),1,0)+IF(ISNUMBER(D16),1,0)+IF(ISNUMBER(E16),1,0))) | G16: =IF(F16="","",5-F16)
B17: Capability Overall | C17: ='2. Assessment'!J29 | D17: ='2. Assessment'!J41 | E17: ='2. Assessment'!J53
B20: NRR REPORTING — Heatmap
B21: Category | C21: Score | D21: Gap to L5
B22: M1 — Definition & Scope | C22: =IF('2. Assessment'!K10="","",'2. Assessment'!K10) | D22: =IF(C22="","",5-C22)
B23: M2 — Component Capture | C23: =IF('2. Assessment'!K11="","",'2. Assessment'!K11) | D23: =IF(C23="","",5-C23)
B24: M3 — Calculation Method | C24: =IF('2. Assessment'!K12="","",'2. Assessment'!K12) | D24: =IF(C24="","",5-C24)
B25: M4 — Granularity | C25: =IF('2. Assessment'!K13="","",'2. Assessment'!K13) | D25: =IF(C25="","",5-C25)
B26: M5 — Cadence | C26: =IF('2. Assessment'!K14="","",'2. Assessment'!K14) | D26: =IF(C26="","",5-C26)
B27: M6 — Trust & Distribution | C27: =IF('2. Assessment'!K15="","",'2. Assessment'!K15) | D27: =IF(C27="","",5-C27)
B28: M7 — Forward-Looking | C28: =IF('2. Assessment'!K16="","",'2. Assessment'!K16) | D28: =IF(C28="","",5-C28)
B29: Capability Overall (weighted) | C29: ='2. Assessment'!J17 | D29: =IF(C29="","",5-C29)
B31: REVENUE RETENTION — Heatmap
B32: Lever | C32: People | D32: Process | E32: Technology | F32: Data | G32: Lever Avg | H32: Gap to L5
B33: L1 — Impact Engine | C33: =IF('2. Assessment'!K22="","",'2. Assessment'!K22) | D33: =IF('2. Assessment'!L22="","",'2. Assessment'!L22) | E33: =IF('2. Assessment'!M22="","",'2. Assessment'!M22) | F33: =IF('2. Assessment'!N22="","",'2. Assessment'!N22) | G33: =IF('2. Assessment'!J22="","",'2. Assessment'!J22) | H33: =IF(G33="","",5-G33)
B34: L2 — Whitespace | C34: =IF('2. Assessment'!K23="","",'2. Assessment'!K23) | D34: =IF('2. Assessment'!L23="","",'2. Assessment'!L23) | E34: =IF('2. Assessment'!M23="","",'2. Assessment'!M23) | F34: =IF('2. Assessment'!N23="","",'2. Assessment'!N23) | G34: =IF('2. Assessment'!J23="","",'2. Assessment'!J23) | H34: =IF(G34="","",5-G34)
B35: L3 — Account Plan | C35: =IF('2. Assessment'!K24="","",'2. Assessment'!K24) | D35: =IF('2. Assessment'!L24="","",'2. Assessment'!L24) | E35: =IF('2. Assessment'!M24="","",'2. Assessment'!M24) | F35: =IF('2. Assessment'!N24="","",'2. Assessment'!N24) | G35: =IF('2. Assessment'!J24="","",'2. Assessment'!J24) | H35: =IF(G35="","",5-G35)
B36: L4 — Plays | C36: =IF('2. Assessment'!K25="","",'2. Assessment'!K25) | D36: =IF('2. Assessment'!L25="","",'2. Assessment'!L25) | E36: =IF('2. Assessment'!M25="","",'2. Assessment'!M25) | F36: =IF('2. Assessment'!N25="","",'2. Assessment'!N25) | G36: =IF('2. Assessment'!J25="","",'2. Assessment'!J25) | H36: =IF(G36="","",5-G36)
B37: L5 — Execution | C37: =IF('2. Assessment'!K26="","",'2. Assessment'!K26) | D37: =IF('2. Assessment'!L26="","",'2. Assessment'!L26) | E37: =IF('2. Assessment'!M26="","",'2. Assessment'!M26) | F37: =IF('2. Assessment'!N26="","",'2. Assessment'!N26) | G37: =IF('2. Assessment'!J26="","",'2. Assessment'!J26) | H37: =IF(G37="","",5-G37)
B38: L6 — Incentives | C38: =IF('2. Assessment'!K27="","",'2. Assessment'!K27) | D38: =IF('2. Assessment'!L27="","",'2. Assessment'!L27) | E38: =IF('2. Assessment'!M27="","",'2. Assessment'!M27) | F38: =IF('2. Assessment'!N27="","",'2. Assessment'!N27) | G38: =IF('2. Assessment'!J27="","",'2. Assessment'!J27) | H38: =IF(G38="","",5-G38)
B39: L7 — Governance | C39: =IF('2. Assessment'!K28="","",'2. Assessment'!K28) | D39: =IF('2. Assessment'!L28="","",'2. Assessment'!L28) | E39: =IF('2. Assessment'!M28="","",'2. Assessment'!M28) | F39: =IF('2. Assessment'!N28="","",'2. Assessment'!N28) | G39: =IF('2. Assessment'!J28="","",'2. Assessment'!J28) | H39: =IF(G39="","",5-G39)
B40: Dim Avg (weighted) | C40: ='2. Assessment'!F29 | D40: ='2. Assessment'!G29 | E40: ='2. Assessment'!H29 | F40: ='2. Assessment'!I29 | G40: ='2. Assessment'!J29
B42: REVENUE EXPANSION — Heatmap
B43: Lever | C43: People | D43: Process | E43: Technology | F43: Data | G43: Lever Avg | H43: Gap to L5
B44: L1 — Impact Engine | C44: =IF('2. Assessment'!K34="","",'2. Assessment'!K34) | D44: =IF('2. Assessment'!L34="","",'2. Assessment'!L34) | E44: =IF('2. Assessment'!M34="","",'2. Assessment'!M34) | F44: =IF('2. Assessment'!N34="","",'2. Assessment'!N34) | G44: =IF('2. Assessment'!J34="","",'2. Assessment'!J34) | H44: =IF(G44="","",5-G44)
B45: L2 — Whitespace | C45: =IF('2. Assessment'!K35="","",'2. Assessment'!K35) | D45: =IF('2. Assessment'!L35="","",'2. Assessment'!L35) | E45: =IF('2. Assessment'!M35="","",'2. Assessment'!M35) | F45: =IF('2. Assessment'!N35="","",'2. Assessment'!N35) | G45: =IF('2. Assessment'!J35="","",'2. Assessment'!J35) | H45: =IF(G45="","",5-G45)
B46: L3 — Account Plan | C46: =IF('2. Assessment'!K36="","",'2. Assessment'!K36) | D46: =IF('2. Assessment'!L36="","",'2. Assessment'!L36) | E46: =IF('2. Assessment'!M36="","",'2. Assessment'!M36) | F46: =IF('2. Assessment'!N36="","",'2. Assessment'!N36) | G46: =IF('2. Assessment'!J36="","",'2. Assessment'!J36) | H46: =IF(G46="","",5-G46)
B47: L4 — Plays | C47: =IF('2. Assessment'!K37="","",'2. Assessment'!K37) | D47: =IF('2. Assessment'!L37="","",'2. Assessment'!L37) | E47: =IF('2. Assessment'!M37="","",'2. Assessment'!M37) | F47: =IF('2. Assessment'!N37="","",'2. Assessment'!N37) | G47: =IF('2. Assessment'!J37="","",'2. Assessment'!J37) | H47: =IF(G47="","",5-G47)
B48: L5 — Execution | C48: =IF('2. Assessment'!K38="","",'2. Assessment'!K38) | D48: =IF('2. Assessment'!L38="","",'2. Assessment'!L38) | E48: =IF('2. Assessment'!M38="","",'2. Assessment'!M38) | F48: =IF('2. Assessment'!N38="","",'2. Assessment'!N38) | G48: =IF('2. Assessment'!J38="","",'2. Assessment'!J38) | H48: =IF(G48="","",5-G48)
B49: L6 — Incentives | C49: =IF('2. Assessment'!K39="","",'2. Assessment'!K39) | D49: =IF('2. Assessment'!L39="","",'2. Assessment'!L39) | E49: =IF('2. Assessment'!M39="","",'2. Assessment'!M39) | F49: =IF('2. Assessment'!N39="","",'2. Assessment'!N39) | G49: =IF('2. Assessment'!J39="","",'2. Assessment'!J39) | H49: =IF(G49="","",5-G49)
B50: L7 — Governance | C50: =IF('2. Assessment'!K40="","",'2. Assessment'!K40) | D50: =IF('2. Assessment'!L40="","",'2. Assessment'!L40) | E50: =IF('2. Assessment'!M40="","",'2. Assessment'!M40) | F50: =IF('2. Assessment'!N40="","",'2. Assessment'!N40) | G50: =IF('2. Assessment'!J40="","",'2. Assessment'!J40) | H50: =IF(G50="","",5-G50)
B51: Dim Avg (weighted) | C51: ='2. Assessment'!F41 | D51: ='2. Assessment'!G41 | E51: ='2. Assessment'!H41 | F51: ='2. Assessment'!I41 | G51: ='2. Assessment'!J41
B53: PRICING OPTIMIZATION — Heatmap
B54: Lever | C54: People | D54: Process | E54: Technology | F54: Data | G54: Lever Avg | H54: Gap to L5
B55: L1 — Impact Engine | C55: =IF('2. Assessment'!K46="","",'2. Assessment'!K46) | D55: =IF('2. Assessment'!L46="","",'2. Assessment'!L46) | E55: =IF('2. Assessment'!M46="","",'2. Assessment'!M46) | F55: =IF('2. Assessment'!N46="","",'2. Assessment'!N46) | G55: =IF('2. Assessment'!J46="","",'2. Assessment'!J46) | H55: =IF(G55="","",5-G55)
B56: L2 — Whitespace | C56: =IF('2. Assessment'!K47="","",'2. Assessment'!K47) | D56: =IF('2. Assessment'!L47="","",'2. Assessment'!L47) | E56: =IF('2. Assessment'!M47="","",'2. Assessment'!M47) | F56: =IF('2. Assessment'!N47="","",'2. Assessment'!N47) | G56: =IF('2. Assessment'!J47="","",'2. Assessment'!J47) | H56: =IF(G56="","",5-G56)
B57: L3 — Account Plan | C57: =IF('2. Assessment'!K48="","",'2. Assessment'!K48) | D57: =IF('2. Assessment'!L48="","",'2. Assessment'!L48) | E57: =IF('2. Assessment'!M48="","",'2. Assessment'!M48) | F57: =IF('2. Assessment'!N48="","",'2. Assessment'!N48) | G57: =IF('2. Assessment'!J48="","",'2. Assessment'!J48) | H57: =IF(G57="","",5-G57)
B58: L4 — Plays | C58: =IF('2. Assessment'!K49="","",'2. Assessment'!K49) | D58: =IF('2. Assessment'!L49="","",'2. Assessment'!L49) | E58: =IF('2. Assessment'!M49="","",'2. Assessment'!M49) | F58: =IF('2. Assessment'!N49="","",'2. Assessment'!N49) | G58: =IF('2. Assessment'!J49="","",'2. Assessment'!J49) | H58: =IF(G58="","",5-G58)
B59: L5 — Execution | C59: =IF('2. Assessment'!K50="","",'2. Assessment'!K50) | D59: =IF('2. Assessment'!L50="","",'2. Assessment'!L50) | E59: =IF('2. Assessment'!M50="","",'2. Assessment'!M50) | F59: =IF('2. Assessment'!N50="","",'2. Assessment'!N50) | G59: =IF('2. Assessment'!J50="","",'2. Assessment'!J50) | H59: =IF(G59="","",5-G59)
B60: L6 — Incentives | C60: =IF('2. Assessment'!K51="","",'2. Assessment'!K51) | D60: =IF('2. Assessment'!L51="","",'2. Assessment'!L51) | E60: =IF('2. Assessment'!M51="","",'2. Assessment'!M51) | F60: =IF('2. Assessment'!N51="","",'2. Assessment'!N51) | G60: =IF('2. Assessment'!J51="","",'2. Assessment'!J51) | H60: =IF(G60="","",5-G60)
B61: L7 — Governance | C61: =IF('2. Assessment'!K52="","",'2. Assessment'!K52) | D61: =IF('2. Assessment'!L52="","",'2. Assessment'!L52) | E61: =IF('2. Assessment'!M52="","",'2. Assessment'!M52) | F61: =IF('2. Assessment'!N52="","",'2. Assessment'!N52) | G61: =IF('2. Assessment'!J52="","",'2. Assessment'!J52) | H61: =IF(G61="","",5-G61)
B62: Dim Avg (weighted) | C62: ='2. Assessment'!F53 | D62: ='2. Assessment'!G53 | E62: ='2. Assessment'!H53 | F62: ='2. Assessment'!I53 | G62: ='2. Assessment'!J53

Sheet 4. Rubric
B2: LOREMEX · NRR INTELLIGENCE
B3: Rubric
B5: INTELLIGENCE LADDER
B6: Level | C6: Name | D6: Posture | E6: What it looks like
B7: 1 | C7: Ad Hoc | D7: Blind | E7: No reliable view; instinct-driven decisions; people-only, no tooling or data substrate.
B8: 2 | C8: Assigned | D8: Reactive | E8: Data is captured somewhere but used after the fact; manual stitching; a few people do the work.
B9: 3 | C9: Accountable | D9: Diagnostic | E9: Data is joined and tooled; team can answer 'why' with effort; standardized process; clear ownership.
B10: 4 | C10: Optimised | D10: Predictive | E10: Systems flag what's coming; near-real-time signals route work; closed-loop measurement and governance.
B11: 5 | C11: Predictive | D11: Intelligent | E11: System senses, predicts, recommends, acts, and learns; continuously refined; effort is leveraged.
B14: FULL RUBRIC — every (capability × lever × dimension) ladder
B15: These are the descriptors that appear in the Assessment tab dropdowns. Each capability has its own ladder.
B17: NRR REPORTING
B18: Category | C18: 1 Ad Hoc | D18: 2 Assigned | E18: 3 Accountable | F18: 4 Optimised | G18: 5 Predictive
B19: M1 Definition & Scope | C19: No agreed definition — teams use different versions; conversations derail on what 'NRR' even means. | D19: Informal definition exists; one analyst owns it; partial documentation; inconsistent across reports. | E19: Single documented definition owned by Finance / RevOps; followed consistently across all NRR reports. | F19: Definition under change-control; versions tracked; refreshed on cadence with audit trail. | G19: Continuously refined; automated consistency checks; data lineage tracked end-to-end.
B20: M2 Component Capture | C20: Components extracted ad-hoc each period via manual spreadsheet exports; heavy reconciliation pain. | D20: One analyst pulls components manually; partial automation; reconciliation issues are common. | E20: Standardized component capture documented and followed; automated extraction from billing / CRM. | F20: Integrated component pipeline; near-real-time capture; variance flagged automatically. | G20: System captures and validates components autonomously; anomalies caught proactively.
B21: M3 Calculation Method | C21: Calculated in spreadsheets; method varies by analyst; formula errors common; results not reproducible. | D21: Calculation steps documented but inconsistent in practice; reconciliation issues across periods. | E21: Calculation version-controlled in BI / dbt models; reproducible across periods; team trained. | F21: Calculation audited each cycle; variances investigated; cross-team validation in place. | G21: Continuously refined and outcome-tested; autonomous validation; closed-loop refinement.
B22: M4 Granularity | C22: NRR available only at company level; no slicing capability. | D22: Some slicing on ad-hoc request; inconsistent definitions across cuts; partial coverage. | E22: Standardized slicing across product, segment, cohort, geo, tenure with consistent definitions. | F22: Self-serve cohort analysis; cross-cut consistency governed; predictive cohorting available. | G22: Natural-language slicing; agentic cohort discovery; system surfaces meaningful cuts.
B23: M5 Cadence | C23: Reported quarterly with weeks of lag; the number feels 'after the fact' by the time it lands. | D23: Monthly reporting but heavy manual prep; lag of days; not actionable in-cycle. | E23: Monthly cadence with standardized prep; automated refresh; reliable monthly delivery. | F23: Weekly / on-demand reporting; near-real-time pipeline; current within a day. | G23: Continuous refresh; live numbers; system flags shifts as they happen.
B24: M6 Trust & Distribution | C24: Number disputed at every readout; data sources contradictory; reconciliation impossible. | D24: Used internally but not trusted at exec level; reconciled but stakeholders still dispute. | E24: Trusted at department / function level; standardized distribution to leadership. | F24: Trusted at exec level; informs strategic decisions; integrated into operating reviews. | G24: Trusted at board level; basis for valuation; self-serve at all levels with explained variances.
B25: M7 Forward-Looking | C25: Only historical NRR reported; no forward view; no leading indicators captured. | D25: Some forecasts attempted ad hoc based on rep gut-feel; leading indicators partial. | E25: Documented forecast methodology with leading indicators; produced each cycle by Finance / RevOps. | F25: Governed forecast with variance-to-actuals tracking; predictive analytics integrated. | G25: Continuously refined autonomous forecast; ML scenario planning; outcome-tested.
B27: REVENUE RETENTION
B28: Lever | C28: Dim | D28: 1 Ad Hoc | E28: 2 Assigned | F28: 3 Accountable | G28: 4 Optimised | H28: 5 Predictive
B29: L1 Impact Engine | C29: People | D29: No one quantifies value for renewal; relationship-only. | E29: One or two CSMs build value recaps for renewals ad hoc. | F29: Trained CSMs articulate value evidence per account on a cadence. | G29: CSMs coached on value signals; QBR-driven; segmented by tier. | H29: System surfaces value gaps automatically; CSMs handle exceptions.
C30: Process | D30: No method to assemble value evidence for renewal. | E30: Ad-hoc value recaps stitched manually each renewal cycle. | F30: Standardized value-realization review on a renewal cadence. | G30: Reviewed, audited, governed across the renewal portfolio. | H30: Process autonomous; system runs value review; humans handle exceptions.
C31: Technology | D31: Nothing instrumented for value tracking; spreadsheets and slide decks. | E31: Basic CS tool tracks usage; partial CRM integration. | F31: CS platform with health scores tied to renewal hub. | G31: Integrated stack — CS, CRM, product, billing, support. | H31: AI-native; predictive models flag renewal slippage automatically.
C32: Data | D32: No reliable outcome data; finance system only. | E32: Some usage data captured but stale, partial, unjoined. | F32: Joined customer 360 refreshed regularly; powers health. | G32: Near-real-time customer data graph with predictive features. | H32: Data substrate autonomous; quality and lineage governed.
B33: L2 Whitespace | C33: People | D33: No one watches for renewal risk; surprises at renewal. | E33: Some CSMs flag risk reactively when an account flares up. | F33: Trained CSMs watch risk signals on a cadence; clear escalation. | G33: Risk specialists coached; segmented coverage; outcomes tracked. | H33: Risk team leveraged by system; humans handle complex risk.
C34: Process | D34: No risk-scoring method; risk is whatever the CSM feels. | E34: Health score exists in one tool but stale or ignored. | F34: Standardized risk-scoring model with defined triggers. | G34: Risk model governed, audited, A/B-tested; closed-loop. | H34: Risk detection and routing partially autonomous.
C35: Technology | D35: No risk tooling; reviewed only when account flares. | E35: Basic CS health score; partial coverage; manual analysis. | F35: Risk-scoring tool runs across base; signals joined and visible. | G35: Risk model current; routes to owners with full context. | H35: AI-native; risk model learns from outcomes; agentic interventions.
C36: Data | D36: Risk signal data missing, stale, or unjoined. | E36: Partial signal data; manual joins; stale by the time used. | F36: Joined signal data (usage, sentiment, support); refreshed. | G36: Near-real-time risk signal graph with predictive features. | H36: Data substrate enables autonomous risk detection; lineage governed.
B37: L3 Account Plan | C37: People | D37: No retention plans; everything in the CSM's head. | E37: Some CSMs keep retention plans in shared docs; inconsistent. | F37: CSMs trained to build retention plans tied to live signals. | G37: Plans coached against renewal outcomes; segmented by tier. | H37: System recommends next moves; CSMs make strategic decisions.
C38: Process | D38: No template or cadence for retention planning. | E38: Plans in shared docs; stale by renewal time. | F38: Standardized retention plan template, kept current, coached against. | G38: Plans auto-update from live signals; governed cadence. | H38: Plans prescriptive; system suggests moves; humans handle exceptions.
C39: Technology | D39: Retention plans in stale Word docs or nothing. | E39: Plans in shared cloud docs; no live data attached. | F39: Plans live in CS platform with live signal references. | G39: Plans integrated with CRM, CS, signals; auto-refresh. | H39: AI-native plan system; agentic suggestions; closed-loop.
C40: Data | D40: Plans not anchored in real data; rep notes only. | E40: Plans reference some data manually pulled; stale. | F40: Plans reference current usage, health, outcome data. | G40: Plans pull near-real-time joined data; ML-ready. | H40: Data enables plan automation; quality governed.
B41: L4 Plays | C41: People | D41: No retention plays; teams improvise when signals fire. | E41: A few CSMs run save plays; manual triggers; inconsistent. | F41: CSMs trained on named retention plays (save, sponsor change, usage drop). | G41: Specialized owners coached on play execution; outcomes tracked. | H41: System leverages team; humans run exception plays only.
C42: Process | D42: No defined retention play library; ad-hoc response. | E42: A few plays documented; manual alerts; uneven application. | F42: Comprehensive retention play library with triggers, owners, SLAs. | G42: Plays governed, audited, A/B-tested. | H42: System detects retention signals, routes plays, refines.
C43: Technology | D43: No tooling; retention signals missed or noticed by accident. | E43: Manual alerts; assignments tracked in spreadsheets. | F43: Systems detect retention triggers and route plays with context. | G43: Automated trigger-to-action; outcomes tracked end-to-end. | H43: Agentic workflows initiate retention plays; closed-loop learning.
C44: Data | D44: Retention signal data not joined; triggers undetectable. | E44: Triggers detected manually after the fact. | F44: Joined signal data; retention triggers detectable in time. | G44: Near-real-time signal graph with predictive triggering. | H44: System learns which plays land on which retention signals.
B45: L5 Execution | C45: People | D45: No coaching on renewal motion; CSMs improvise. | E45: Some CSMs follow a method; uneven skill at renewals. | F45: All CSMs coached on stage-gated renewal motion; certified. | G45: Renewal coaching tied to live data; segmented by tier. | H45: System recommends next-best-action per stage; CSMs handle complex saves.
C46: Process | D46: No defined renewal motion or stage gates. | E46: Loose renewal stages; data captured inconsistently. | F46: Standardized renewal motion with stage gates; instrumented. | G46: Renewal motion measured end-to-end; A/B-tested; coached against outcomes. | H46: Renewal motion partially autonomous; system runs routine.
C47: Technology | D47: No CRM stages for renewals; tracked in spreadsheets. | E47: Basic CRM renewal stages; manual approval and tracking. | F47: CRM / CS / e-sign integrated for renewals end-to-end. | G47: Best-of-breed renewal stack; live forecast feed. | H47: AI-native renewal motion; agentic execution.
C48: Data | D48: Renewal pipeline data unreliable or incomplete. | E48: Renewal pipeline data exists but stale or disputed. | F48: Renewal pipeline data trustworthy and current; powers forecast. | G48: Near-real-time renewal pipeline; predictive forecast. | H48: Data substrate for autonomous renewal decisions.
B49: L6 Incentives | C49: People | D49: CSMs unsure how retention behavior maps to comp. | E49: Some retention metrics tied to comp but unclear or disputed. | F49: CSMs trained on comp model; clear line behavior-to-payout. | G49: Retention comp coached against performance; reinforced via deal desk. | H49: Continuous comp tuning from retention outcome data.
C50: Process | D50: Comp doesn't reward retention; CSMs focus elsewhere. | E50: Some retention credit exists but partial; attribution disputed. | F50: Comp engineered for GRR, on-time renewals, save rate. | G50: Retention comp governed, audited, integrated with performance management. | H50: Comp model continuously refined from retention outcomes.
C51: Technology | D51: Retention comp calculated manually in spreadsheets. | E51: Basic comp tool; partial integration with CS metrics. | F51: Integrated comp platform tied to retention metrics. | G51: Retention comp metrics live; tied to dashboards. | H51: AI-native comp engine recommends retention model tuning.
C52: Data | D52: Retention attribution data dirty or contested. | E52: Attribution exists but disputed; manual reconciliation. | F52: Retention attribution clean; single source of truth. | G52: Retention attribution current and trusted; powers dashboards. | H52: Data substrate enables continuous retention comp optimization.
B53: L7 Governance | C53: People | D53: No named retention owner; metrics not trusted. | E53: Informal retention owner; occasional reviews; static reports. | F53: Clear retention owner; regular cadence; trusted dashboard. | G53: Exec-level retention governance; segment owners drive numbers. | H53: Board-visible retention program with predictive metrics.
C54: Process | D54: No cadence for retention reviews; metrics not reported. | E54: Ad-hoc retention reviews; reports lag the action. | F54: Regular retention cadence (forecast, risk, post-renewal); followed. | G54: Exec retention cadence; integrated with broader business reviews. | H54: Retention cadence partially autonomous; system surfaces issues.
C55: Technology | D55: No retention dashboards; metrics in spreadsheets after the fact. | E55: Basic retention dashboards but stale or disputed. | F55: Trusted retention dashboards exist and update reliably. | G55: Live exec retention dashboards integrated across systems. | H55: AI-native retention dashboards; predictive metrics flag reversals.
C56: Data | D56: Retention metrics not trusted; data dirty or disputed. | E56: Some retention metrics tracked but disputed by stakeholders. | F56: Retention metrics (GRR, at-risk $) trusted at department level. | G56: Retention metrics trusted at exec level; current and joined. | H56: Retention metrics trusted at board level; predictive.
B58: REVENUE EXPANSION
B59: Lever | C59: Dim | D59: 1 Ad Hoc | E59: 2 Assigned | F59: 3 Accountable | G59: 4 Optimised | H59: 5 Predictive
B60: L1 Impact Engine | C60: People | D60: No one quantifies value per unit; pure feature pitch. | E60: One or two AEs build value cases ad hoc per deal. | F60: Trained AEs articulate value per seat / token / run on cadence. | G60: AEs coached on value signals; segmented by expansion motion. | H60: System surfaces value automatically; AEs handle high-value moves.
C61: Process | D61: No method to show value justifies expansion. | E61: Ad-hoc value notes stitched per expansion conversation. | F61: Standardized value-per-unit review on a cadence. | G61: Reviewed, audited, governed across expansion portfolio. | H61: Process autonomous; system runs review; humans handle exceptions.
C62: Technology | D62: Nothing instrumented for usage-value tracking; spreadsheets only. | E62: Basic product analytics; partial CRM integration. | F62: Value tooling tied to accounts; integrated with CRM and CPQ. | G62: Integrated stack — product, CRM, billing, CPQ; near-real-time. | H62: AI-native; predictive models flag expansion-readiness automatically.
C63: Data | D63: Usage-vs-entitlement data missing or unjoined. | E63: Partial usage data; manual joins; stale. | F63: Clean joined data (active vs licensed, usage per unit, outcomes). | G63: Near-real-time and broad coverage; ML-ready features. | H63: Live, complete, governed; substrate for autonomous decisions.
B64: L2 Whitespace | C64: People | D64: No one ranks accounts for expansion headroom. | E64: Some AEs eyeball headroom ad hoc; reactive to customer ask. | F64: AEs trained to rank seat / usage headroom on a cadence. | G64: Specialized AMs coached on headroom-driven motion. | H64: System surfaces headroom; AEs focus on top-priority moves.
C65: Process | D65: No repeatable method to detect or score expansion headroom. | E65: Manual whitespace analysis once a quarter; partial. | F65: Standardized whitespace scoring documented and applied. | G65: Whitespace scoring governed, audited, A/B-tested. | H65: Detection and routing partially autonomous.
C66: Technology | D66: No whitespace tool; eyeballing only. | E66: Basic pacing dashboard or single-tool view. | F66: Whitespace tool surfaces headroom; sortable across base. | G66: Best-of-breed stack with real-time signals; auto-routing. | H66: AI-native; predictive whitespace models; agentic plays.
C67: Data | D67: Entitlement / usage data missing or unjoined. | E67: Partial data; manual joins; stale. | F67: Joined entitlement, usage, product-fit data refreshed regularly. | G67: Near-real-time signal graph with predictive features. | H67: Live, complete data substrate; governed quality.
B68: L3 Account Plan | C68: People | D68: No expansion plans; planning in heads. | E68: Some AEs keep expansion plans in shared docs; inconsistent. | F68: AEs trained to build expansion plans tied to live signals. | G68: Plans coached against expansion outcomes; segmented by motion. | H68: System suggests next moves; AEs make strategic decisions.
C69: Process | D69: No template or cadence for expansion planning. | E69: Plans in shared docs; stale by the time used. | F69: Standardized expansion plan template, kept current. | G69: Plans auto-update from live signals; governed. | H69: Plans prescriptive; system recommends moves; humans handle exceptions.
C70: Technology | D70: Expansion plans in stale Word docs or nothing. | E70: Plans in shared cloud docs; no live data attached. | F70: Plans live in CRM with live signal references. | G70: Plans integrated with CRM and signals; auto-refresh. | H70: AI-native plan system; agentic suggestions; closed-loop.
C71: Data | D71: Plans not anchored in real data; rep notes only. | E71: Plans reference some data manually pulled; stale. | F71: Plans reference current usage, outcome, stakeholder data. | G71: Plans pull near-real-time joined data; ML-ready. | H71: Data enables plan automation; quality governed.
B72: L4 Plays | C72: People | D72: No expansion plays; teams improvise when customer asks. | E72: A few AEs run a few plays; manual triggers; inconsistent. | F72: AEs trained on named expansion plays (commit, overage, role change). | G72: Specialized AEs coached on play execution; outcomes tracked. | H72: System leverages team; humans run exception plays only.
C73: Process | D73: No defined expansion play library. | E73: A few plays documented; manual alerts; uneven application. | F73: Comprehensive expansion play library with triggers and SLAs. | G73: Plays governed and A/B-tested. | H73: System detects expansion signals, routes plays, refines.
C74: Technology | D74: No tooling; expansion signals missed. | E74: Manual alerts; assignments tracked in spreadsheets. | F74: Systems detect expansion triggers and route plays with context. | G74: Automated trigger-to-action; outcomes tracked end-to-end. | H74: Agentic workflows initiate expansion plays; closed-loop learning.
C75: Data | D75: Expansion signal data not joined. | E75: Triggers detected manually after the fact. | F75: Joined signal data; expansion triggers detectable in time. | G75: Near-real-time signal graph with predictive triggering. | H75: System learns which plays land on which expansion signals.
B76: L5 Execution | C76: People | D76: No coaching on usage-up motion; AEs improvise. | E76: Some AEs follow a method; uneven skill at expansion. | F76: All AEs coached on stage-gated usage-up motion; certified. | G76: Motion coaching tied to live data; segmented by tier. | H76: System recommends next-best-action per stage; AEs handle complex deals.
C77: Process | D77: No defined usage-up motion. | E77: Loose stages; data captured inconsistently. | F77: Standardized usage-up motion with stage gates; instrumented. | G77: Motion measured end-to-end; A/B-tested. | H77: Motion partially autonomous; system runs routine.
C78: Technology | D78: No CRM stages for expansion; tracked in spreadsheets. | E78: Basic CRM stages; manual approval. | F78: CRM / CPQ / e-sign integrated; usage-aware CPQ. | G78: Best-of-breed expansion stack; live forecast feed. | H78: AI-native expansion motion; agentic execution.
C79: Data | D79: Expansion pipeline data unreliable or incomplete. | E79: Pipeline data exists but stale or disputed. | F79: Expansion pipeline data trustworthy and current. | G79: Near-real-time pipeline graph with predictive forecast. | H79: Data substrate for autonomous expansion decisions.
B80: L6 Incentives | C80: People | D80: AEs unsure how usage growth maps to comp. | E80: Some expansion metrics tied to comp but unclear or disputed. | F80: AEs trained on comp model; clear line behavior-to-payout. | G80: Expansion comp coached against performance. | H80: Continuous comp tuning from expansion outcome data.
C81: Process | D81: Comp ignores usage growth; rewards new logos only. | E81: Some expansion credit exists but partial; attribution disputed. | F81: Comp engineered for usage growth, tier-up, cross-sell. | G81: Expansion comp governed, audited, integrated. | H81: Comp model continuously refined from expansion outcomes.
C82: Technology | D82: Expansion comp calculated manually. | E82: Basic comp tool; partial CRM integration. | F82: Integrated comp platform tied to expansion metrics. | G82: Expansion comp metrics live and current. | H82: AI-native comp engine recommends expansion model tuning.
C83: Data | D83: Expansion attribution data dirty or contested. | E83: Attribution exists but disputed; manual reconciliation. | F83: Expansion attribution clean; single source of truth. | G83: Attribution current and trusted; powers dashboards. | H83: Data enables continuous expansion comp optimization.
B84: L7 Governance | C84: People | D84: No named expansion owner. | E84: Informal expansion owner; occasional reviews; static reports. | F84: Clear expansion owner; regular cadence; trusted dashboard. | G84: Exec-level expansion governance; segment owners drive. | H84: Board-visible expansion program with predictive metrics.
C85: Process | D85: No cadence for expansion reviews. | E85: Ad-hoc expansion reviews; reports lag the action. | F85: Regular cadence (consumption, commit utilization, forecast). | G85: Exec cadence; integrated with business reviews. | H85: Cadence partially autonomous; system surfaces issues.
C86: Technology | D86: No expansion dashboards. | E86: Basic expansion dashboards but stale or disputed. | F86: Trusted expansion dashboards update reliably. | G86: Live exec expansion dashboards integrated across systems. | H86: AI-native expansion dashboards; predictive metrics.
C87: Data | D87: Expansion metrics not trusted. | E87: Some expansion metrics tracked but disputed. | F87: Expansion metrics trusted at department level. | G87: Expansion metrics trusted at exec level; current and joined. | H87: Expansion metrics trusted at board level; predictive.
B89: PRICING OPTIMIZATION
B90: Lever | C90: Dim | D90: 1 Ad Hoc | E90: 2 Assigned | F90: 3 Accountable | G90: 4 Optimised | H90: 5 Predictive
B91: L1 Impact Engine | C91: People | D91: Price set on cost-plus or competitor; no value anchoring. | E91: Some reps reference value at quote time; inconsistent. | F91: Reps and deal desk trained on value-based pricing. | G91: Reps coached on value signals; segment owners drive pricing. | H91: System recommends price floors; reps focus on strategic deals.
C92: Process | D92: No method to anchor price on realized value. | E92: Some value rationales in slides per deal; inconsistent. | F92: Standardized value-based pricing method at quote time. | G92: Method reviewed, audited, governed across segments. | H92: Method partially autonomous; system suggests floors per segment.
C93: Technology | D93: No CPQ value tooling; spreadsheet quotes. | E93: Basic CPQ; manual value evidence at quote time. | F93: CPQ pulls realized-value evidence at quote time. | G93: Integrated value-pricing tooling; near-real-time evidence. | H93: AI-native pricing engine recommends list and floor per segment.
C94: Data | D94: Value-realization data not joined to deals. | E94: Some value data manually pulled into deals; stale. | F94: Value data joined to deal records; refreshed regularly. | G94: Near-real-time value data with predictive features. | H94: Data substrate enables autonomous price recommendations.
B95: L2 Whitespace | C95: People | D95: No one watches for leakage; effective price drift invisible. | E95: Some analysts look at pricing data ad hoc. | F95: Pricing analyst / deal desk watches leakage on a cadence. | G95: Specialized pricing team coached on leakage detection. | H95: System surfaces leakage; team focuses on strategic re-pricing.
C96: Process | D96: No leakage-detection method. | E96: Manual leakage analysis once a quarter; partial. | F96: Standardized leakage scoring documented and applied. | G96: Leakage detection governed, audited, A/B-tested. | H96: Detection and routing partially autonomous.
C97: Technology | D97: No pricing leakage tooling. | E97: Basic price reports; partial coverage. | F97: Leakage scoring tool runs across base; sortable. | G97: Best-of-breed pricing analytics with real-time signals. | H97: AI-native; predictive leakage models; agentic re-pricing.
C98: Data | D98: Deal-level pricing data missing or unjoined. | E98: Partial pricing data; manual joins; stale. | F98: Joined deal data (price, discount, segment, win / loss). | G98: Near-real-time pricing data graph; predictive features. | H98: Live, complete pricing data substrate; governed.
B99: L3 Account Plan | C99: People | D99: No segment-level pricing strategy; one global price list. | E99: Some segment owners keep pricing rules in slides. | F99: Segment owners trained to set per-segment strategy with floors. | G99: Strategy coached against win / loss outcomes; segmented. | H99: System recommends strategy per segment; owners decide.
C100: Process | D100: No template or cadence for pricing strategy. | E100: Pricing rules in slides; not enforced at quote. | F100: Standardized strategy template per segment, kept current. | G100: Strategies auto-update from live signals; governed. | H100: Strategy prescriptive; system recommends targets per segment.
C101: Technology | D101: Pricing strategy in slides or nothing. | E101: Strategy in shared docs; no CPQ enforcement. | F101: Strategy integrated with CPQ and approval workflows. | G101: Strategy integrated with live elasticity data. | H101: AI-native; agentic strategy adjustments per segment.
C102: Data | D102: Strategy not anchored in real data; gut-feel. | E102: Strategy references some data manually; stale. | F102: Strategy references current win / loss and elasticity data. | G102: Strategy pulls near-real-time joined data; ML-ready. | H102: Data enables strategy automation; quality governed.
B103: L4 Plays | C103: People | D103: No pricing plays; case-by-case decisions. | E103: A few deal desk plays; manual approval flow. | F103: Deal desk trained on named pricing plays (re-price, escalate, re-tier). | G103: Specialized owners coached on pricing play execution. | H103: System leverages team; humans handle exception plays.
C104: Process | D104: No defined pricing play library. | E104: Manual approval rules for some discounts. | F104: Comprehensive pricing play library with triggers and SLAs. | G104: Plays governed and A/B-tested. | H104: System detects pricing triggers, routes plays, refines.
C105: Technology | D105: No tooling; pricing decisions case-by-case. | E105: Basic discount approvals in CPQ. | F105: Systems detect pricing triggers and route plays. | G105: Automated trigger-to-action; outcomes tracked end-to-end. | H105: Agentic workflows initiate pricing plays; closed-loop learning.
C106: Data | D106: Pricing trigger data not joined. | E106: Triggers detected manually after the fact. | F106: Joined signal data; pricing triggers detectable in time. | G106: Near-real-time signal graph with predictive triggering. | H106: System learns which plays land on which pricing signals.
B107: L5 Execution | C107: People | D107: No coaching on pricing motion; reps improvise. | E107: Some reps follow a method; uneven skill at price defense. | F107: All reps coached on stage-gated pricing motion; certified. | G107: Pricing coaching tied to live data; segmented by tier. | H107: System recommends next-best-action per stage.
C108: Process | D108: No defined pricing motion. | E108: Loose stages; approvals slow and inconsistent. | F108: Standardized pricing motion with stage gates and guardrails. | G108: Motion measured end-to-end; A/B-tested. | H108: Motion partially autonomous; system runs routine approvals.
...

Sheet 5. NRR Semantics
B2: LOREMEX · NRR INTELLIGENCE
B3: NRR Semantics — confirm or edit
B5: Classification rules behind the NRR calculator. Carried from your existing NRR_Calculations.xlsx.
B7: DEFINITIONS
B8: Component | C8: Definition (per period) | D8: Excludes
B9: Starting period base | C9: Established from the 2 months prior to each measured period. | D9: New-logo revenue; accounts in only one baseline month.
B10: Expansion | C10: Positive recurring delta within existing accounts. | D10: New logos; reactivation of churned accounts.
B11: Contraction | C11: Negative recurring delta within retained accounts. | D11: Full-logo loss (that is churn).
B12: Churn | C12: Full-logo loss: account recurring revenue → $0 vs prior period. | D12: Partial downgrades (those are contraction).
B14: KEY DECISIONS (confirm)
B15: # | C15: Question | D15: Options | E15: Your answer
B16: Q1 | C16: Starting base for a period? | D16: (a) Both baseline months required; starting MRR = average (b) Both required; starting MRR = most recent (c) Other | E16: a
B17: Q2 | C17: Cohort entry — mid-period new logos? | D17: (a) Must be active in BOTH baseline months (b) Active in either month (c) Other | E17: a
B18: Q3 | C18: Churn threshold (vs contraction)? | D18: (a) Recurring revenue reaches exactly $0 (b) Falls below floor $X (c) Other | E18: a
B19: Q4 | C19: Small downgrade — contraction or churn? | D19: (a) Contraction (still a customer) (b) Churn if below floor (c) Other | E19: a
B20: Q5 | C20: Net at account level, or separate per product? | D20: (a) Separate per product, NOT netted (PRD default) (b) Net at account (c) Other | E20: a
B21: Q6 | C21: Reactivated account (churned then returned)? | D21: (a) New logo (b) Expansion (c) Its own 'reactivation' line (d) Other | E21: c
B22: Q7 | C22: Period grain? | D22: (a) Monthly (b) Quarterly (c) Both, tenant-selectable | E22: c
B23: Q8 | C23: Cohort lock — same anchor across later periods? | D23: (a) Lock to anchor month (b) Rolling cohort (c) Other | E23: b
B24: Q9 | C24: Can a finished NRR % be entered directly? | D24: (a) No — only computed (b) Allow manual override with confidence flag | E24: a
B25: Q10 | C25: When a component is missing, what happens to that period? | D25: (a) Don't render (b) Render with lowered confidence (c) Hand-enter component | E25: b, c

Sheet _rubric
A1: 1 — No agreed definition — teams use different versions; conversations derail on what 'NRR' even means.
A2: 2 — Informal definition exists; one analyst owns it; partial documentation; inconsistent across reports.
A3: 3 — Single documented definition owned by Finance / RevOps; followed consistently across all NRR reports.
A4: 4 — Definition under change-control; versions tracked; refreshed on cadence with audit trail.
A5: 5 — Continuously refined; automated consistency checks; data lineage tracked end-to-end.
A6: 1 — Components extracted ad-hoc each period via manual spreadsheet exports; heavy reconciliation pain.
A7: 2 — One analyst pulls components manually; partial automation; reconciliation issues are common.
A8: 3 — Standardized component capture documented and followed; automated extraction from billing / CRM.
A9: 4 — Integrated component pipeline; near-real-time capture; variance flagged automatically.
A10: 5 — System captures and validates components autonomously; anomalies caught proactively.
A11: 1 — Calculated in spreadsheets; method varies by analyst; formula errors common; results not reproducible.
A12: 2 — Calculation steps documented but inconsistent in practice; reconciliation issues across periods.
... A455: 5 — Pricing metrics trusted at board level; predictive.
